pulp_hugging_face/__init__.py
pulp_hugging_face/app/__init__.py
pulp_hugging_face/app/apps.py
pulp_hugging_face/app/handler.py
pulp_hugging_face/app/models.py
pulp_hugging_face/app/serializers.py
pulp_hugging_face/app/settings.py
pulp_hugging_face/app/urls.py
pulp_hugging_face/app/utils.py
pulp_hugging_face/app/views.py
pulp_hugging_face/app/viewsets.py
pulp_hugging_face/app/migrations/0001_initial.py
pulp_hugging_face/app/migrations/__init__.py
pulp_hugging_face/app/tasks/__init__.py
pulp_hugging_face/app/tasks/publishing.py
pulp_hugging_face/app/tasks/synchronizing.py
pulp_hugging_face/tests/__init__.py
pulp_hugging_face/tests/functional/__init__.py
pulp_hugging_face/tests/functional/api/__init__.py
pulp_hugging_face/tests/performance/__init__.py
pulp_hugging_face/tests/unit/__init__.py
pulp_hugging_face/tests/upgrade/__init__.py
pulp_hugging_face/tests/upgrade/post/__init__.py
pulp_hugging_face/tests/upgrade/pre/__init__.py
pulp_hugging_face-0.3.0.dist-info/licenses/LICENSE
pulp_hugging_face-0.3.0.dist-info/METADATA
pulp_hugging_face-0.3.0.dist-info/WHEEL
pulp_hugging_face-0.3.0.dist-info/entry_points.txt
pulp_hugging_face-0.3.0.dist-info/top_level.txt
pulp_hugging_face-0.3.0.dist-info/RECORD
