Metadata-Version: 2.4
Name: pulp-hugging-face
Version: 0.3.0
Summary: pulp-hugging-face plugin for the Pulp Project
Author-email: Yasen Trahnov <yasen@trahnov.eu>
Project-URL: Homepage, https://pulpproject.org/
Project-URL: Documentation, https://github.com/pulp/pulp_hugging_face/blob/main/README.md
Project-URL: Repository, https://github.com/pulp/pulp_hugging_face
Project-URL: Bug Tracker, https://github.com/pulp/pulp_hugging_face/issues
Project-URL: Changelog, https://github.com/pulp/pulp_hugging_face/blob/main/CHANGES.md
Classifier: License :: OSI Approved :: GNU General Public License v2 or later (GPLv2+)
Classifier: Operating System :: POSIX :: Linux
Classifier: Framework :: Django
Classifier: Programming Language :: Python
Classifier: Programming Language :: Python :: 3
Classifier: Programming Language :: Python :: 3.9
Classifier: Programming Language :: Python :: 3.10
Classifier: Programming Language :: Python :: 3.11
Classifier: Programming Language :: Python :: 3.12
Requires-Python: >=3.9
License-File: LICENSE
Requires-Dist: pulpcore<3.115,>=3.100.0
Requires-Dist: httpx<1.0.0,>=0.24.0
Dynamic: license-file
